README.md
setup.py
zboard/__init__.py
zboard/__main__.py
zboard/_canonical_names.py
zboard/_darwinkeyboard.py
zboard/_darwinmouse.py
zboard/_generic.py
zboard/_keyboard_event.py
zboard/_keyboard_tests.py
zboard/_mouse_event.py
zboard/_mouse_tests.py
zboard/_nixcommon.py
zboard/_nixkeyboard.py
zboard/_nixmouse.py
zboard/_winkeyboard.py
zboard/_winmouse.py
zboard/mouse.py
zboard.egg-info/PKG-INFO
zboard.egg-info/SOURCES.txt
zboard.egg-info/dependency_links.txt
zboard.egg-info/requires.txt
zboard.egg-info/top_level.txt