Metadata-Version: 2.1
Name: zboard
Version: 0.3
Summary: Hook and simulate keyboard events on Windows and Linux
Home-page: https://github.com/zebaxhfi/zboard
Author: zebax
Author-email: zzuhaibtariq1998@gmail.com
License: UNKNOWN
Keywords: keyboard hook simulate hotkey
Platform: UNKNOWN
Classifier: Development Status :: 4 - Beta
Classifier: License :: OSI Approved :: MIT License
Classifier: Operating System :: Microsoft :: Windows
Classifier: Operating System :: Unix
Classifier: Operating System :: MacOS :: MacOS X
Classifier: Programming Language :: Python :: 2
Classifier: Programming Language :: Python :: 3
Classifier: Topic :: Software Development :: Libraries :: Python Modules
Classifier: Topic :: Utilities
